odoo10_addon_customer_pricing_in_product_view-10.0.1.0.0-py2.7-nspkg.pth
odoo/addons/customer_pricing_in_product_view/README.rst
odoo/addons/customer_pricing_in_product_view/__init__.py
odoo/addons/customer_pricing_in_product_view/__manifest__.py
odoo/addons/customer_pricing_in_product_view/models/__init__.py
odoo/addons/customer_pricing_in_product_view/models/res_partner.py
odoo/addons/customer_pricing_in_product_view/views/res_partner_view.xml
odoo10_addon_customer_pricing_in_product_view-10.0.1.0.0.dist-info/DESCRIPTION.rst
odoo10_addon_customer_pricing_in_product_view-10.0.1.0.0.dist-info/METADATA
odoo10_addon_customer_pricing_in_product_view-10.0.1.0.0.dist-info/RECORD
odoo10_addon_customer_pricing_in_product_view-10.0.1.0.0.dist-info/WHEEL
odoo10_addon_customer_pricing_in_product_view-10.0.1.0.0.dist-info/metadata.json
odoo10_addon_customer_pricing_in_product_view-10.0.1.0.0.dist-info/namespace_packages.txt
odoo10_addon_customer_pricing_in_product_view-10.0.1.0.0.dist-info/top_level.txt
