Metadata-Version: 2.0
Name: odoo10-addon-customer-pricing-in-product-view
Version: 10.0.1.0.0
Summary: Display Customer Price in Product View
Home-page: http://odoo-community.org
Author: Odoo Community Association (OCA), O4SB - Graeme Gellatly
Author-email: support@odoo-community.org
License: AGPL-3
Platform: UNKNOWN
Classifier: Programming Language :: Python :: 2.7
Classifier: Framework :: Odoo
Classifier: License :: OSI Approved :: GNU Affero General Public License v3
Requires-Dist: odoo (<10.1dev,>=10.0)
